{
  "name": "pangulu_100x_suite",
  "metric": "makespan",
  "workload_concurrency": 1,
  "workloads": [
    {
        "name": "ASIC_100ks",
        "path": "tmp/ASIC_100ks_pangulu_gstrf_workload_1024_flops100x.json",
        "weight": 1.0
    },
    {
        "name": "email",
        "path": "tmp/email-EuAll_pangulu_gstrf_workload_1024_flops100x.json",
        "weight": 1.0
    },
    {
        "name": "bfwa782",
        "path": "tmp/bfwa782_pangulu_gstrf_workload_flops100x.json",
        "weight": 1.0
    },
    {
        "name": "trefethen",
        "path": "tmp/trefethen_pangulu_gstrf_workload_flops100x.json",
        "weight": 1.0
    }
  ]
}